eliottree/__init__.py
eliottree/_cli.py
eliottree/_color.py
eliottree/_compat.py
eliottree/_errors.py
eliottree/_parse.py
eliottree/_render.py
eliottree/_theme.py
eliottree/_util.py
eliottree/_version.py
eliottree/filter.py
eliottree/format.py
eliottree/tree.py
eliottree/newsfragments/.gitignore
eliottree/test/__init__.py
eliottree/test/matchers.py
eliottree/test/tasks.py
eliottree/test/test_cli.py
eliottree/test/test_compat.py
eliottree/test/test_filter.py
eliottree/test/test_format.py
eliottree/test/test_render.py
eliottree/test/test_util.py
eliottree/tree_format/LICENSE
eliottree/tree_format/__init__.py
eliottree/tree_format/_text.py
eliottree/tree_format/tests/__init__.py
eliottree/tree_format/tests/test_text.py
eliot_tree-24.0.0.dist-info/LICENSE
eliot_tree-24.0.0.dist-info/METADATA
eliot_tree-24.0.0.dist-info/WHEEL
eliot_tree-24.0.0.dist-info/entry_points.txt
eliot_tree-24.0.0.dist-info/top_level.txt
eliot_tree-24.0.0.dist-info/RECORD
