Metadata-Version: 2.1
Name: eliot-tree
Version: 24.0.0
Summary: Render Eliot logs as an ASCII tree
Home-page: https://github.com/jonathanj/eliottree
Author: Jonathan Jacobs
Author-email: jonathan@jsphere.com
Maintainer: Jonathan Jacobs
Maintainer-email: jonathan@jsphere.com
License: MIT
Platform: UNKNOWN
Classifier: Development Status :: 3 - Alpha
Classifier: Topic :: System :: Logging
Classifier: Intended Audience :: Developers
Classifier: Intended Audience :: System Administrators
Classifier: License :: OSI Approved :: MIT License
Classifier: Operating System :: OS Independent
Classifier: Programming Language :: Python
Requires-Dist: six >=1.13.0
Requires-Dist: jmespath >=0.7.1
Requires-Dist: iso8601 >=0.1.10
Requires-Dist: colored >=1.4.2
Requires-Dist: toolz >=0.8.2
Requires-Dist: eliot >=1.6.0
Requires-Dist: win-unicode-console >=0.5 ; platform_system == "Windows"
Provides-Extra: test
Requires-Dist: testtools >=1.8.0 ; extra == 'test'
